[
  {
    "english": "obfuscate",
    "indonesia": "Membingungkan",
    "definisi": "Membuat sesuatu menjadi tidak jelas atau sulit dipahami.",
    "sentence": "Penjelasan yang bertele-tele hanya membingungkan para siswa."
  },
  {
    "english": "palpable",
    "indonesia": "Nyata",
    "definisi": "Dapat dirasakan atau disentuh; jelas terlihat atau terasa.",
    "sentence": "Ketegangan di ruangan itu sangat nyata saat rapat berlangsung."
  },
  {
    "english": "quixotic",
    "indonesia": "Mustahil",
    "definisi": "Sangat idealis atau tidak realistis.",
    "sentence": "Usahanya untuk mengubah dunia dalam semalam dianggap mustahil oleh banyak orang."
  },
  {
    "english": "recalcitrant",
    "indonesia": "Bandel",
    "definisi": "Menolak untuk patuh atau sulit diatur.",
    "sentence": "Anak itu sangat bandel dan sering kali tidak mendengarkan orang tuanya."
  },
  {
    "english": "sagacious",
    "indonesia": "Bijaksana",
    "definisi": "Memiliki penilaian yang baik dan bijaksana.",
    "sentence": "Keputusan bijaksana itu menyelamatkan perusahaan dari kebangkrutan."
  },
  {
    "english": "tenuous",
    "indonesia": "Rapuh",
    "definisi": "Sangat lemah atau tipis; mudah hancur.",
    "sentence": "Hubungan antara dua negara itu sangat rapuh dan mudah retak."
  },
  {
    "english": "ubiquitous",
    "indonesia": "Ada di mana-mana",
    "definisi": "Ditemukan di mana-mana; sangat umum.",
    "sentence": "Smartphone sekarang sudah ada di mana-mana, dimiliki oleh hampir semua orang."
  },
  {
    "english": "vacillate",
    "indonesia": "Ragu-ragu",
    "definisi": "Berubah-ubah dalam membuat keputusan atau pendirian.",
    "sentence": "Dia sering ragu-ragu dalam mengambil langkah penting dalam hidupnya."
  },
  {
    "english": "wane",
    "indonesia": "Memudar",
    "definisi": "Menjadi berkurang atau lemah.",
    "sentence": "Semangatnya mulai memudar setelah beberapa kali gagal dalam ujian."
  },
  {
    "english": "xenophobia",
    "indonesia": "Ketakutan terhadap orang asing",
    "definisi": "Ketakutan atau prasangka terhadap orang asing atau sesuatu yang asing.",
    "sentence": "Gerakan anti-imigran tersebut dipicu oleh ketakutan terhadap orang asing."
  },
  {
    "english": "yield",
    "indonesia": "Menyerah",
    "definisi": "Memberikan jalan atau menyerah pada tekanan.",
    "sentence": "Akhirnya dia menyerah pada permintaan orang tuanya untuk melanjutkan studi."
  },
  {
    "english": "zealous",
    "indonesia": "Bertekad kuat",
    "definisi": "Sangat antusias atau bersemangat terhadap suatu tujuan.",
    "sentence": "Dia bertekad kuat untuk menyelesaikan proyek ini tepat waktu."
  },
  {
    "english": "aberration",
    "indonesia": "Penyimpangan",
    "definisi": "Penyimpangan dari apa yang normal atau diharapkan.",
    "sentence": "Perilaku anehnya dianggap sebagai penyimpangan dari norma masyarakat."
  },
  {
    "english": "belligerent",
    "indonesia": "Agresif",
    "definisi": "Cenderung berkelahi atau bermusuhan.",
    "sentence": "Sikap agresifnya sering kali membuat orang lain merasa tidak nyaman."
  },
  {
    "english": "cacophony",
    "indonesia": "Kekacauan suara",
    "definisi": "Kombinasi suara yang tidak harmonis dan tidak menyenangkan.",
    "sentence": "Di tengah kekacauan suara pasar, saya tidak bisa mendengar suara teman saya."
  },
  {
    "english": "debilitate",
    "indonesia": "Melemahkan",
    "definisi": "Membuat seseorang atau sesuatu menjadi lemah.",
    "sentence": "Penyakit kronis itu telah melemahkan tubuhnya selama bertahun-tahun."
  },
  {
    "english": "ebullient",
    "indonesia": "Bersemangat tinggi",
    "definisi": "Sangat antusias dan energik.",
    "sentence": "Anak-anak bersemangat tinggi saat bermain di taman."
  },
  {
    "english": "facetious",
    "indonesia": "Bercanda",
    "definisi": "Tidak serius; bersikap lucu atau bercanda pada waktu yang tidak tepat.",
    "sentence": "Komentar bercandanya dianggap tidak sopan dalam suasana duka."
  },
  {
    "english": "garrulous",
    "indonesia": "Banyak bicara",
    "definisi": "Cenderung berbicara banyak, terutama tentang hal-hal yang tidak penting.",
    "sentence": "Nenek sering kali banyak bicara tentang masa lalunya yang indah."
  }
]